SpectrogramUtils/__init__.py
SpectrogramUtils/_version.py
SpectrogramUtils/data/__init__.py
SpectrogramUtils/data/compatibility.py
SpectrogramUtils/data/config.py
SpectrogramUtils/data/data.py
SpectrogramUtils/data/librosa_stft_args.py
SpectrogramUtils/data/types.py
SpectrogramUtils/exceptions/__init__.py
SpectrogramUtils/exceptions/lib_exceptions.py
SpectrogramUtils/extensions/__init__.py
SpectrogramUtils/extensions/tf/__init__.py
SpectrogramUtils/extensions/torch/__init__.py
SpectrogramUtils/misc/__init__.py
SpectrogramUtils/misc/utils.py
SpectrogramUtils/processors/__init__.py
SpectrogramUtils/processors/abstract_data_processor.py
SpectrogramUtils/processors/scaler_audio_processor.py
SpectrogramUtils/processors/simple_scaling_processor.py
SpectrogramUtils/processors/wrapper.py
SpectrogramUtils/spectrogram/__init__.py
SpectrogramUtils/spectrogram/multi_spectrogram.py
SpectrogramUtils/spectrogram/spectrogram_factory.py
SpectrogramUtils/spectrogram/spectrogram_factory_tf.py
SpectrogramUtils/spectrogram/spectrogram_factory_torch.py
SpectrogramUtils/stft_complexe_processor/__init__.py
SpectrogramUtils/stft_complexe_processor/abstract_stft_processor.py
SpectrogramUtils/stft_complexe_processor/mag_phase_stft_processor.py
SpectrogramUtils/stft_complexe_processor/real_imag_stft_processor.py
SpectrogramUtils-0.4.7.dist-info/LICENSE
SpectrogramUtils-0.4.7.dist-info/METADATA
SpectrogramUtils-0.4.7.dist-info/WHEEL
SpectrogramUtils-0.4.7.dist-info/top_level.txt
SpectrogramUtils-0.4.7.dist-info/RECORD
