Metadata-Version: 2.1
Name: SpectrogramUtils
Version: 0.4.7
Summary: Make usage of spectrogram easy
Home-page: https://github.com/sacha-renault/SpectrogramUtils/tree/release
Author: Sacha Renault
Author-email: 
License: MIT
Classifier: Programming Language :: Python :: 3
Classifier: License :: OSI Approved :: MIT License
Classifier: Operating System :: OS Independent
Requires-Python: >=3.6
License-File: LICENSE
Requires-Dist: numpy
Requires-Dist: librosa
Requires-Dist: soundfile
Requires-Dist: matplotlib
Requires-Dist: scikit-learn
